<?xml version="1.0" encoding="UTF-8"?>
<objects serializationModel="Studio.02.03.00">
	<object class="AudioFile" id="{97ea1a7a-a616-4ec7-92c0-8aa09e3dfc9a}">
		<property name="assetPath">
			<value>Clients/Food/error.wav</value>
		</property>
		<property name="frequencyInKHz">
			<value>44.0999985</value>
		</property>
		<property name="channelCount">
			<value>2</value>
		</property>
		<property name="length">
			<value>0.94911564625850342</value>
		</property>
		<relationship name="masterAssetFolder">
			<destination>{94131936-2e02-4ded-95e2-d3ee51328358}</destination>
		</relationship>
	</object>
</objects>
